<?xml version="1.0" encoding="UTF-8" ?>
<!DOCTYPE generatorConfiguration PUBLIC "-//mybatis.org//DTD MyBatis Generator Configuration 1.0//EN" "http://mybatis.org/dtd/mybatis-generator-config_1_0.dtd" >
<generatorConfiguration >
  <context id="context1" >
    <jdbcConnection driverClass="com.mysql.jdbc.Driver" connectionURL="jdbc:mysql://localhost:3306/trainingdb" userId="root" password="123456" />
    <javaModelGenerator targetPackage="com.insigma.pojo" targetProject="OnlineRegistration" />
    <sqlMapGenerator targetPackage="com.insigma.mapper" targetProject="OnlineRegistration" />
<!--     <javaClientGenerator targetPackage="com.insigma.mapper" targetProject="OnlineRegistration" type="XMLMAPPER" /> -->

<!--     <table tableName="t_accessory" enableCountByExample="false" enableUpdateByExample="false" -->
<!-- 	enableDeleteByExample="false" enableSelectByExample="false" -->
<!-- 	selectByExampleQueryId="false"></table> -->
<!--     <table tableName="t_admin" enableCountByExample="false" enableUpdateByExample="false" -->
<!-- 	enableDeleteByExample="false" enableSelectByExample="false" -->
<!-- 	selectByExampleQueryId="false"></table> -->
<!--     <table tableName="t_area" enableCountByExample="false" enableUpdateByExample="false" -->
<!-- 	enableDeleteByExample="false" enableSelectByExample="false" -->
<!-- 	selectByExampleQueryId="false"></table> -->
<!--     <table tableName="t_city" enableCountByExample="false" enableUpdateByExample="false" -->
<!-- 	enableDeleteByExample="false" enableSelectByExample="false" -->
<!-- 	selectByExampleQueryId="false"></table> -->
<!--     <table tableName="t_class" enableCountByExample="false" enableUpdateByExample="false" -->
<!-- 	enableDeleteByExample="false" enableSelectByExample="false" -->
<!-- 	selectByExampleQueryId="false"></table> -->
<!--     <table tableName="t_class_remark" enableCountByExample="false" enableUpdateByExample="false" -->
<!-- 	enableDeleteByExample="false" enableSelectByExample="false" -->
<!-- 	selectByExampleQueryId="false"></table> -->
<!--     <table tableName="t_course" enableCountByExample="false" enableUpdateByExample="false" -->
<!-- 	enableDeleteByExample="false" enableSelectByExample="false" -->
<!-- 	selectByExampleQueryId="false"></table> -->
<!--     <table tableName="t_course_sub" enableCountByExample="false" enableUpdateByExample="false" -->
<!-- 	enableDeleteByExample="false" enableSelectByExample="false" -->
<!-- 	selectByExampleQueryId="false"></table> -->
<!--     <table tableName="t_course_sup" enableCountByExample="false" enableUpdateByExample="false" -->
<!-- 	enableDeleteByExample="false" enableSelectByExample="false" -->
<!-- 	selectByExampleQueryId="false"></table> -->
<!--     <table tableName="t_note" enableCountByExample="false" enableUpdateByExample="false" -->
<!-- 	enableDeleteByExample="false" enableSelectByExample="false" -->
<!-- 	selectByExampleQueryId="false"></table> -->
<!--     <table tableName="t_province" enableCountByExample="false" enableUpdateByExample="false" -->
<!-- 	enableDeleteByExample="false" enableSelectByExample="false" -->
<!-- 	selectByExampleQueryId="false"></table> -->
<!--     <table tableName="t_register_apply" enableCountByExample="false" enableUpdateByExample="false" -->
<!-- 	enableDeleteByExample="false" enableSelectByExample="false" -->
<!-- 	selectByExampleQueryId="false"></table> -->
<!--     <table tableName="t_remark" enableCountByExample="false" enableUpdateByExample="false" -->
<!-- 	enableDeleteByExample="false" enableSelectByExample="false" -->
<!-- 	selectByExampleQueryId="false"></table> -->
    <table tableName="t_reply" enableCountByExample="false" enableUpdateByExample="false"
	enableDeleteByExample="false" enableSelectByExample="false"
	selectByExampleQueryId="false"></table>
<!--     <table tableName="t_score" enableCountByExample="false" enableUpdateByExample="false" -->
<!-- 	enableDeleteByExample="false" enableSelectByExample="false" -->
<!-- 	selectByExampleQueryId="false"></table> -->
<!--     <table tableName="t_student" enableCountByExample="false" enableUpdateByExample="false" -->
<!-- 	enableDeleteByExample="false" enableSelectByExample="false" -->
<!-- 	selectByExampleQueryId="false"></table> -->
  </context>
</generatorConfiguration>